Workbook

Sheet App Checklist
A1: Cluster Manager Store Visit Checklist - Computer Application Format
A3: Store Name | D3: Store Code | G3: Visit Date | H3: 46136.445 | J3: Audit Type | K3: Full Visit
A4: Cluster Manager | D4: Store Manager | G4: City / Region | J4: Visit Status | K4: Draft
A6: Total Questions | B6: =COUNTA(B10:B49) -> 39 | D6: Answered | E6: =COUNTIF(D10:D49,"Yes")+COUNTIF(D10:D49,"No")+COUNTIF(D10:D49,"NA") -> 0 | G6: Open Actions | H6: =COUNTIF(K10:K49,"Open")+COUNTIF(K10:K49,"In Progress") -> 40 | J6: Compliance % | K6: =IFERROR(SUM(L10:L49)/(COUNTIF(D10:D49,"Yes")+COUNTIF(D10:D49,"No")),0) -> 0
A9: ID | B9: Section | C9: Checklist Question | D9: Response | E9: Evidence / Measurement Needed | F9: Observation / Findings | G9: Photo / Attachment Ref. | H9: Action Required | I9: Owner | J9: Due Date | K9: Action Status | L9: Score
A10: CM-001 | C10: Is Target vs Achievement reviewed for the store and all departments? | E10: MTD Ach % to be mentioned in a text box | H10: 1. 2. 3. | K10: Open | L10: =IF(D10="Yes",1,IF(D10="No",0,""))
A11: CM-002 | B11: Sales | C11: Is gap analysis conducted for underperformance? | H11: 1. 2. 3. | K11: Open | L11: =IF(D11="Yes",1,IF(D11="No",0,""))
A12: CM-003 | B12: Sales | C12: Is a clear action plan defined for improvement?(Dept by dept) | H12: 1. 2. 3. | K12: Open | L12: =IF(D12="Yes",1,IF(D12="No",0,""))
A13: CM-004 | B13: Margin | C13: Is FTD/MTD margin reviewed? | E13: Target Margin % - Actual Margin % - | H13: 1. 2. 3. | K13: Open | L13: =IF(D13="Yes",1,IF(D13="No",0,""))
A14: CM-005 | B14: Margin | C14: Are margin improvement actions identified and tracked? | H14: 1. 2. 3. | K14: Open | L14: =IF(D14="Yes",1,IF(D14="No",0,""))
A15: CM-006 | B15: Inventory | C15: Is GRN closure completed as per P2P process? | E15: Pending Supplier GRN post 24 Hrs - Pending WH GRNs post 24 HRS - | H15: 1. 2. 3. | K15: Open | L15: =IF(D15="Yes",1,IF(D15="No",0,""))
A16: CM-007 | B16: Inventory | C16: Are dump & shrink monitored regularly? | E16: Dump % - Shrink % - | H16: 1. 2. 3. | K16: Open | L16: =IF(D16="Yes",1,IF(D16="No",0,""))
A17: CM-008 | B17: Inventory | C17: Is SIT pending reviewed? | H17: 1. 2. 3. | K17: Open | L17: =IF(D17="Yes",1,IF(D17="No",0,""))
A18: CM-009 | B18: Inventory | C18: Are expiry and non-moving items tracked? | E18: Total Expiry Qty - Total Expiry Value - | H18: 1. 2. 3. | K18: Open | L18: =IF(D18="Yes",1,IF(D18="No",0,""))
A19: CM-010 | B19: Inventory | C19: Is Shrinkage RCA and action plan implemented? | H19: 1. 2. 3. | K19: Open | L19: =IF(D19="Yes",1,IF(D19="No",0,""))
A20: CM-011 | B20: Inventory | C20: Is perpetual inventory/HV count conducted? | E20: Observations | H20: 1. 2. 3. | K20: Open | L20: =IF(D20="Yes",1,IF(D20="No",0,""))
A21: CM-012 | B21: Inventory | C21: Are RTV processes followed? | E21: Observations | H21: 1. 2. 3. | K21: Open | L21: =IF(D21="Yes",1,IF(D21="No",0,""))
A22: CM-013 | B22: Inventory | C22: Is negative stock reviewed and corrected? | E22: Total Negative OH Items - Total Negative Stock Value - | H22: 1. 2. 3. | K22: Open | L22: =IF(D22="Yes",1,IF(D22="No",0,""))
A23: CM-014 | B23: Manpower | C23: Is manpower as per plan vs actual reviewed? | E23: Mention key manpower gaps | H23: 1. 2. 3. | K23: Open | L23: =IF(D23="Yes",1,IF(D23="No",0,""))
A24: CM-015 | B24: Manpower | C24: Is attrition analyzed with reasons? | H24: 1. 2. 3. | K24: Open | L24: =IF(D24="Yes",1,IF(D24="No",0,""))
A25: CM-016 | B25: Manpower | C25: Is HR scorecard reviewed? | H25: 1. 2. 3. | K25: Open | L25: =IF(D25="Yes",1,IF(D25="No",0,""))
A26: CM-017 | B26: Housekeeping | C26: Is store cleanliness maintained? | E26: Front of Store - Yes / No F&V section - Yes / No Lose staples section - Yes / No Washrooms - Yes / No back Room - Yes /No | H26: 1. 2. 3. | K26: Open | L26: =IF(D26="Yes",1,IF(D26="No",0,""))
A27: CM-018 | B27: Housekeeping | C27: Is housekeeping manpower adequate? | H27: 1. 2. 3. | K27: Open | L27: =IF(D27="Yes",1,IF(D27="No",0,""))
A28: CM-019 | B28: Security | C28: Are security duties and posts reviewed? | H28: 1. 2. 3. | K28: Open | L28: =IF(D28="Yes",1,IF(D28="No",0,""))
A29: CM-020 | B29: Cash | C29: Is cash shortage/excess monitored and resolved? | H29: 1. 2. 3. | K29: Open | L29: =IF(D29="Yes",1,IF(D29="No",0,""))
A30: CM-021 | B30: Store Display | C30: Is the merchandise display neat and clean? | H30: 1. 2. 3. | K30: Open | L30: =IF(D30="Yes",1,IF(D30="No",0,""))
A31: CM-022 | B31: Store Display | C31: Is proper signage available? | H31: 1. 2. 3. | K31: Open | L31: =IF(D31="Yes",1,IF(D31="No",0,""))
A32: CM-023 | B32: Store Display | C32: Is price/size communication clear? | H32: 1. 2. 3. | K32: Open | L32: =IF(D32="Yes",1,IF(D32="No",0,""))
A33: CM-024 | B33: Store Display | C33: Are there any stocks in the floor without security tags? (Check 10 samples) | H33: 1. 2. 3. | K33: Open | L33: =IF(D33="Yes",1,IF(D33="No",0,""))
A34: CM-025 | B34: SOP | C34: Is billing SOP followed correctly? (Observe 5 customer billings and note the feedback) | H34: 1. 2. 3. | K34: Open | L34: =IF(D34="Yes",1,IF(D34="No",0,""))
A35: CM-026 | B35: Parking | C35: Is parking area clean and well managed? | H35: 1. 2. 3. | K35: Open | L35: =IF(D35="Yes",1,IF(D35="No",0,""))
A36: CM-027 | B36: Compliance | C36: Are all statutory licenses valid and available? | H36: 1. 2. 3. | K36: Open | L36: =IF(D36="Yes",1,IF(D36="No",0,""))
A37: CM-028 | B37: Compliance | C37: Are compliance issues identified and addressed? | H37: 1. 2. 3. | K37: Open | L37: =IF(D37="Yes",1,IF(D37="No",0,""))
A38: CM-029 | B38: Maintenance | C38: Are maintenance issues identified and resolved? | H38: 1. 2. 3. | K38: Open | L38: =IF(D38="Yes",1,IF(D38="No",0,""))
... A45: CM-036 | B45: Returns | C45: Are bills verified for all returns in the exchange register? | H45: 1. 2. 3. | K45: Open | L45: =IF(D45="Yes",1,IF(D45="No",0,""))
A46: CM-037 | B46: Finance | C46: Is petty cash audited monthly? | E46: Share the results of the last petty cash audit | H46: 1. 2. 3. | K46: Open | L46: =IF(D46="Yes",1,IF(D46="No",0,""))
A47: CM-038 | B47: Customer | C47: Is customer feedback reviewed and closed? (Feedback Register) | H47: 1. 2. 3. | K47: Open | L47: =IF(D47="Yes",1,IF(D47="No",0,""))
A48: CM-039 | B48: CCTV | C48: Is CCTV footage checked regularly? | H48: 1. 2. 3. | K48: Open | L48: =IF(D48="Yes",1,IF(D48="No",0,""))
A49: CM-040 | B49: Staff | C49: Is staff dining area clean? | H49: 1. 2. 3. | K49: Open | L49: =IF(D49="Yes",1,IF(D49="No",0,""))

Sheet Dashboard
A1: Cluster Manager Visit Dashboard
A3: Store Name | B3: ='App Checklist'!B3 -> 0 | D3: Visit Date | E3: ='App Checklist'!H3 -> 46136.445
A4: Cluster Manager | B4: ='App Checklist'!B4 -> 0 | D4: Audit Type | E4: ='App Checklist'!K3 -> Full Visit
A6: Total Questions | B6: ='App Checklist'!B6 -> 39 | C6: Answered | D6: ='App Checklist'!E6 -> 0 | E6: Open Actions | F6: ='App Checklist'!H6 -> 40 | G6: Compliance % | H6: ='App Checklist'!K6 -> 0
A9: Section | B9: Questions | C9: Yes | D9: No | E9: NA | F9: Compliance % | H9: Status | I9: Count
B10: =COUNTIF('App Checklist'!$B$10:$B$49,A10) -> 0 | C10: =COUNTIFS('App Checklist'!$B$10:$B$49,A10,'App Checklist'!$D$10:$D$49,"Yes") -> 0 | D10: =COUNTIFS('App Checklist'!$B$10:$B$49,A10,'App Checklist'!$D$10:$D$49,"No") -> 0 | E10: =COUNTIFS('App Checklist'!$B$10:$B$49,A10,'App Checklist'!$D$10:$D$49,"NA") -> 0 | F10: =IFERROR(C10/(C10+D10),0) -> 0 | H10: Yes | I10: =COUNTIF('App Checklist'!$D$10:$D$49,"Yes") -> 0
A11: Sales | B11: =COUNTIF('App Checklist'!$B$10:$B$49,A11) -> 2 | C11: =COUNTIFS('App Checklist'!$B$10:$B$49,A11,'App Checklist'!$D$10:$D$49,"Yes") -> 0 | D11: =COUNTIFS('App Checklist'!$B$10:$B$49,A11,'App Checklist'!$D$10:$D$49,"No") -> 0 | E11: =COUNTIFS('App Checklist'!$B$10:$B$49,A11,'App Checklist'!$D$10:$D$49,"NA") -> 0 | F11: =IFERROR(C11/(C11+D11),0) -> 0 | H11: No | I11: =COUNTIF('App Checklist'!$D$10:$D$49,"No") -> 0
A12: Margin | B12: =COUNTIF('App Checklist'!$B$10:$B$49,A12) -> 2 | C12: =COUNTIFS('App Checklist'!$B$10:$B$49,A12,'App Checklist'!$D$10:$D$49,"Yes") -> 0 | D12: =COUNTIFS('App Checklist'!$B$10:$B$49,A12,'App Checklist'!$D$10:$D$49,"No") -> 0 | E12: =COUNTIFS('App Checklist'!$B$10:$B$49,A12,'App Checklist'!$D$10:$D$49,"NA") -> 0 | F12: =IFERROR(C12/(C12+D12),0) -> 0 | H12: NA | I12: =COUNTIF('App Checklist'!$D$10:$D$49,"NA") -> 0
A13: Inventory | B13: =COUNTIF('App Checklist'!$B$10:$B$49,A13) -> 8 | C13: =COUNTIFS('App Checklist'!$B$10:$B$49,A13,'App Checklist'!$D$10:$D$49,"Yes") -> 0 | D13: =COUNTIFS('App Checklist'!$B$10:$B$49,A13,'App Checklist'!$D$10:$D$49,"No") -> 0 | E13: =COUNTIFS('App Checklist'!$B$10:$B$49,A13,'App Checklist'!$D$10:$D$49,"NA") -> 0 | F13: =IFERROR(C13/(C13+D13),0) -> 0
A14: Manpower | B14: =COUNTIF('App Checklist'!$B$10:$B$49,A14) -> 3 | C14: =COUNTIFS('App Checklist'!$B$10:$B$49,A14,'App Checklist'!$D$10:$D$49,"Yes") -> 0 | D14: =COUNTIFS('App Checklist'!$B$10:$B$49,A14,'App Checklist'!$D$10:$D$49,"No") -> 0 | E14: =COUNTIFS('App Checklist'!$B$10:$B$49,A14,'App Checklist'!$D$10:$D$49,"NA") -> 0 | F14: =IFERROR(C14/(C14+D14),0) -> 0
A15: Housekeeping | B15: =COUNTIF('App Checklist'!$B$10:$B$49,A15) -> 2 | C15: =COUNTIFS('App Checklist'!$B$10:$B$49,A15,'App Checklist'!$D$10:$D$49,"Yes") -> 0 | D15: =COUNTIFS('App Checklist'!$B$10:$B$49,A15,'App Checklist'!$D$10:$D$49,"No") -> 0 | E15: =COUNTIFS('App Checklist'!$B$10:$B$49,A15,'App Checklist'!$D$10:$D$49,"NA") -> 0 | F15: =IFERROR(C15/(C15+D15),0) -> 0
A16: Security | B16: =COUNTIF('App Checklist'!$B$10:$B$49,A16) -> 1 | C16: =COUNTIFS('App Checklist'!$B$10:$B$49,A16,'App Checklist'!$D$10:$D$49,"Yes") -> 0 | D16: =COUNTIFS('App Checklist'!$B$10:$B$49,A16,'App Checklist'!$D$10:$D$49,"No") -> 0 | E16: =COUNTIFS('App Checklist'!$B$10:$B$49,A16,'App Checklist'!$D$10:$D$49,"NA") -> 0 | F16: =IFERROR(C16/(C16+D16),0) -> 0
A17: Cash | B17: =COUNTIF('App Checklist'!$B$10:$B$49,A17) -> 1 | C17: =COUNTIFS('App Checklist'!$B$10:$B$49,A17,'App Checklist'!$D$10:$D$49,"Yes") -> 0 | D17: =COUNTIFS('App Checklist'!$B$10:$B$49,A17,'App Checklist'!$D$10:$D$49,"No") -> 0 | E17: =COUNTIFS('App Checklist'!$B$10:$B$49,A17,'App Checklist'!$D$10:$D$49,"NA") -> 0 | F17: =IFERROR(C17/(C17+D17),0) -> 0
A18: Store Display | B18: =COUNTIF('App Checklist'!$B$10:$B$49,A18) -> 4 | C18: =COUNTIFS('App Checklist'!$B$10:$B$49,A18,'App Checklist'!$D$10:$D$49,"Yes") -> 0 | D18: =COUNTIFS('App Checklist'!$B$10:$B$49,A18,'App Checklist'!$D$10:$D$49,"No") -> 0 | E18: =COUNTIFS('App Checklist'!$B$10:$B$49,A18,'App Checklist'!$D$10:$D$49,"NA") -> 0 | F18: =IFERROR(C18/(C18+D18),0) -> 0
A19: SOP | B19: =COUNTIF('App Checklist'!$B$10:$B$49,A19) -> 1 | C19: =COUNTIFS('App Checklist'!$B$10:$B$49,A19,'App Checklist'!$D$10:$D$49,"Yes") -> 0 | D19: =COUNTIFS('App Checklist'!$B$10:$B$49,A19,'App Checklist'!$D$10:$D$49,"No") -> 0 | E19: =COUNTIFS('App Checklist'!$B$10:$B$49,A19,'App Checklist'!$D$10:$D$49,"NA") -> 0 | F19: =IFERROR(C19/(C19+D19),0) -> 0
A20: Parking | B20: =COUNTIF('App Checklist'!$B$10:$B$49,A20) -> 1 | C20: =COUNTIFS('App Checklist'!$B$10:$B$49,A20,'App Checklist'!$D$10:$D$49,"Yes") -> 0 | D20: =COUNTIFS('App Checklist'!$B$10:$B$49,A20,'App Checklist'!$D$10:$D$49,"No") -> 0 | E20: =COUNTIFS('App Checklist'!$B$10:$B$49,A20,'App Checklist'!$D$10:$D$49,"NA") -> 0 | F20: =IFERROR(C20/(C20+D20),0) -> 0
A21: Compliance | B21: =COUNTIF('App Checklist'!$B$10:$B$49,A21) -> 2 | C21: =COUNTIFS('App Checklist'!$B$10:$B$49,A21,'App Checklist'!$D$10:$D$49,"Yes") -> 0 | D21: =COUNTIFS('App Checklist'!$B$10:$B$49,A21,'App Checklist'!$D$10:$D$49,"No") -> 0 | E21: =COUNTIFS('App Checklist'!$B$10:$B$49,A21,'App Checklist'!$D$10:$D$49,"NA") -> 0 | F21: =IFERROR(C21/(C21+D21),0) -> 0
A22: Maintenance | B22: =COUNTIF('App Checklist'!$B$10:$B$49,A22) -> 1 | C22: =COUNTIFS('App Checklist'!$B$10:$B$49,A22,'App Checklist'!$D$10:$D$49,"Yes") -> 0 | D22: =COUNTIFS('App Checklist'!$B$10:$B$49,A22,'App Checklist'!$D$10:$D$49,"No") -> 0 | E22: =COUNTIFS('App Checklist'!$B$10:$B$49,A22,'App Checklist'!$D$10:$D$49,"NA") -> 0 | F22: =IFERROR(C22/(C22+D22),0) -> 0
A23: Fire Safety | B23: =COUNTIF('App Checklist'!$B$10:$B$49,A23) -> 4 | C23: =COUNTIFS('App Checklist'!$B$10:$B$49,A23,'App Checklist'!$D$10:$D$49,"Yes") -> 0 | D23: =COUNTIFS('App Checklist'!$B$10:$B$49,A23,'App Checklist'!$D$10:$D$49,"No") -> 0 | E23: =COUNTIFS('App Checklist'!$B$10:$B$49,A23,'App Checklist'!$D$10:$D$49,"NA") -> 0 | F23: =IFERROR(C23/(C23+D23),0) -> 0
A24: Backroom | B24: =COUNTIF('App Checklist'!$B$10:$B$49,A24) -> 1 | C24: =COUNTIFS('App Checklist'!$B$10:$B$49,A24,'App Checklist'!$D$10:$D$49,"Yes") -> 0 | D24: =COUNTIFS('App Checklist'!$B$10:$B$49,A24,'App Checklist'!$D$10:$D$49,"No") -> 0 | E24: =COUNTIFS('App Checklist'!$B$10:$B$49,A24,'App Checklist'!$D$10:$D$49,"NA") -> 0 | F24: =IFERROR(C24/(C24+D24),0) -> 0
... A29: Staff | B29: =COUNTIF('App Checklist'!$B$10:$B$49,A29) -> 1 | C29: =COUNTIFS('App Checklist'!$B$10:$B$49,A29,'App Checklist'!$D$10:$D$49,"Yes") -> 0 | D29: =COUNTIFS('App Checklist'!$B$10:$B$49,A29,'App Checklist'!$D$10:$D$49,"No") -> 0 | E29: =COUNTIFS('App Checklist'!$B$10:$B$49,A29,'App Checklist'!$D$10:$D$49,"NA") -> 0 | F29: =IFERROR(C29/(C29+D29),0) -> 0

Sheet Lists
A1: Yes | B1: Open | C1: Draft | D1: Full Visit
A2: No | B2: In Progress | C2: Submitted | D2: Follow-up
A3: NA | B3: Closed | C3: Approved | D3: Surprise Audit
B4: Not Required | C4: Revisit Required | D4: Monthly Review

Sheet User Guide
A1: How to Use This Computer-Based Checklist
A3: Step 1 | B3: Fill visit details at the top of the App Checklist sheet.
A4: Step 2 | B4: For each checklist question, select Yes, No, or NA from the Response dropdown.
A5: Step 3 | B5: Enter observations, attach/photo reference numbers, and action plan details where required.
A6: Step 4 | B6: Use Action Status to track Open, In Progress, Closed, or Not Required.
A7: Step 5 | B7: Review the Dashboard sheet for compliance percentage, open actions, and section-wise scores.
A8: Scoring Logic | B8: Yes = 1, No = 0, NA is excluded from compliance percentage.
